{
  "ticket": "ISE-1565",
  "spec": "tests/ISE-1565.spec.ts",
  "analysis": {
    "timestamp": "2026-06-24T15:26:08.391Z",
    "resultsFound": true,
    "status": "passed",
    "totalTests": 8,
    "passedTests": 8,
    "failedTests": 0,
    "flakyTests": [],
    "authFailures": [],
    "brokenSelectors": [],
    "timeoutIssues": [],
    "recommendedFixes": [],
    "pullRequests": [],
    "errorContexts": [],
    "failedTargets": [],
    "recommendations": [],
    "patches": []
  },
  "recommendations": [],
  "patches": [],
  "mcp": {
    "layer": 6,
    "tool": "mcp://playwright/self-heal",
    "ticket": "ISE-1565",
    "spec": "tests/ISE-1565.spec.ts",
    "generatedAt": "2026-06-24T15:26:08.391Z",
    "sessions": [
      {
        "ticket": "ISE-1565",
        "spec": "tests/ISE-1565.spec.ts",
        "command": "npx playwright test tests/ISE-1565.spec.ts --project=chromium --workers=1 --headed",
        "exitCode": 0,
        "status": "passed"
      }
    ],
    "fixes": [],
    "reruns": []
  },
  "timestamp": "2026-06-24T15:26:50.893Z"
}